{
  "users": [
    {
      "name": "Emily",
      "email": "ebventurino@gmail.com",
      "password": "12345",
      "id": 1
    }
  ],
  "favorites": [
    {
      "photoId": "BeTP8JFoCtM",
      "photoUrl": "https://images.unsplash.com/photo-1532622162728-8e7bc97f2c37?ixlib=rb-0.3.5&q=80&fm=jpg&crop=entropy&cs=tinysrgb&w=1080&fit=max&ixid=eyJhcHBfaWQiOjMyMjczfQ&s=2a88d5a3eb8cddd24abdbb2690f284e4",
      "id": "3a1iqsG"
    },
    {
      "photoId": "e3hDxz86IxI",
      "photoUrl": "https://images.unsplash.com/photo-1533529318682-0c3e2fc1e225?ixlib=rb-0.3.5&q=80&fm=jpg&crop=entropy&cs=tinysrgb&w=1080&fit=max&ixid=eyJhcHBfaWQiOjMyMjczfQ&s=e52d2a323f5f99202940e27102d8b11a",
      "UserId": 1,
      "id": "rdzBi5n"
    },
    {
      "photoId": "BgIk55qUlO0",
      "photoUrl": "https://images.unsplash.com/photo-1533496881916-5f7ff85669a0?ixlib=rb-0.3.5&q=80&fm=jpg&crop=entropy&cs=tinysrgb&w=1080&fit=max&ixid=eyJhcHBfaWQiOjMyMjczfQ&s=d591674ebea95389f6dd5bd11d8e9f2c",
      "UserId": 1,
      "id": "eA7BJ0y"
    },
    {
      "photoId": "jv66KlN7jTc",
      "photoUrl": "https://images.unsplash.com/photo-1533498657632-b1ff5543e726?ixlib=rb-0.3.5&q=80&fm=jpg&crop=entropy&cs=tinysrgb&w=1080&fit=max&ixid=eyJhcHBfaWQiOjMyMjczfQ&s=848090dfe95b9809a014d7bb3a7e26bb",
      "UserId": 1,
      "id": "_3IyPOV"
    },
    {
      "photoId": "BgIk55qUlO0",
      "photoUrl": "https://images.unsplash.com/photo-1533496881916-5f7ff85669a0?ixlib=rb-0.3.5&q=80&fm=jpg&crop=entropy&cs=tinysrgb&w=1080&fit=max&ixid=eyJhcHBfaWQiOjMyMjczfQ&s=d591674ebea95389f6dd5bd11d8e9f2c",
      "UserId": 1,
      "id": "oh7kUCZ"
    }
  ],
  "comments": [
    {
      "id": 6
    },
    {
      "message": "testesttest",
      "UserId": 1,
      "id": 7
    }
  ]
}